<?xpacket begin="﻿" id="W5M0MpCehiHzreSzNTczkc9d"?>
<x:xmpmeta xmlns:x="adobe:ns:meta/" x:xmptk="Adobe XMP Core 5.6-c011 79.156380, 2014/06/19-23:40:37        ">
 <rdf:RDF xmlns:rdf="http://www.w3.org/1999/02/22-rdf-syntax-ns#">
  <rdf:Description rdf:about=""
    xmlns:xmp="http://ns.adobe.com/xap/1.0/"
    xmlns:dc="http://purl.org/dc/elements/1.1/"
    xmlns:xmpMM="http://ns.adobe.com/xap/1.0/mm/"
    xmlns:stEvt="http://ns.adobe.com/xap/1.0/sType/ResourceEvent#"
   xmp:CreatorTool="XD"
   xmp:CreateDate="2019-07-31T15:09:53.363-03:00"
   xmp:ModifyDate="2019-09-03T17:25:26.709-03:00"
   xmp:MetadataDate="2019-09-03T17:25:26.709-03:00"
   dc:format="application/vnd.adobe.sparkler.project+dcx"
   xmpMM:DocumentID="e1126419-3aa2-4042-9fc4-bffedde9ec30"
   xmpMM:OriginalDocumentID="e1126419-3aa2-4042-9fc4-bffedde9ec30"
   xmpMM:InstanceID="c198b428-0b3d-49cc-8101-69b37514115e">
   <dc:title>
    <rdf:Alt>
     <rdf:li xml:lang="x-default">layout</rdf:li>
    </rdf:Alt>
   </dc:title>
   <xmpMM:History>
    <rdf:Seq>
     <rdf:li
      stEvt:action="created"
      stEvt:instanceID="e1126419-3aa2-4042-9fc4-bffedde9ec30"
      stEvt:when="2019-07-31T15:09:53.363-03:00"
      stEvt:softwareAgent="XD"/>
     <rdf:li
      stEvt:action="saved"
      stEvt:instanceID="c198b428-0b3d-49cc-8101-69b37514115e"
      stEvt:when="2019-09-03T17:25:26.709-03:00"
      stEvt:softwareAgent="XD"/>
    </rdf:Seq>
   </xmpMM:History>
  </rdf:Description>
 </rdf:RDF>
</x:xmpmeta>
                                                                                                    
                                                                                                    
                                                                                                    
                                                                                                    
                                                                                                    
                                                                                                    
                                                                                                    
                                                                                                    
                                                                                                    
                                                                                                    
                                                                                                    
                                                                                                    
                                                                                                    
                                                                                                    
                                                                                                    
                                                                                                    
                                                                                                    
                                                                                                    
                                                                                                    
                                                                                                    
                           
<?xpacket end="w"?>